tree_sitter_matlab/__init__.py
tree_sitter_matlab/__init__.pyi
tree_sitter_matlab/_binding.abi3.so
tree_sitter_matlab/binding.c
tree_sitter_matlab/py.typed
tree_sitter_matlab/queries/emacs/highlights.scm
tree_sitter_matlab/queries/emacs/textobjects.scm
tree_sitter_matlab/queries/helix/context.scm
tree_sitter_matlab/queries/helix/folds.scm
tree_sitter_matlab/queries/helix/highlights.scm
tree_sitter_matlab/queries/helix/indents.scm
tree_sitter_matlab/queries/helix/injections.scm
tree_sitter_matlab/queries/helix/locals.scm
tree_sitter_matlab/queries/helix/textobjects.scm
tree_sitter_matlab/queries/neovim/context.scm
tree_sitter_matlab/queries/neovim/folds.scm
tree_sitter_matlab/queries/neovim/highlights.scm
tree_sitter_matlab/queries/neovim/indents.scm
tree_sitter_matlab/queries/neovim/injections.scm
tree_sitter_matlab/queries/neovim/locals.scm
tree_sitter_matlab/queries/neovim/tags.scm
tree_sitter_matlab/queries/neovim/textobjects.scm
tree_sitter_matlab-1.2.13.dist-info/METADATA
tree_sitter_matlab-1.2.13.dist-info/WHEEL
tree_sitter_matlab-1.2.13.dist-info/top_level.txt
tree_sitter_matlab-1.2.13.dist-info/RECORD
tree_sitter_matlab-1.2.13.dist-info/licenses/LICENSE
