Metadata-Version: 2.4
Name: tree-sitter-matlab
Version: 1.2.13
Summary: MATLAB tree-sitter parser
Author: Álan Crístoffer e Sousa
License: MIT
Project-URL: Homepage, https://github.com/acristoffers/tree-sitter-matlab
Keywords: incremental,parsing,tree-sitter,matlab
Classifier: Intended Audience :: Developers
Classifier: Topic :: Software Development :: Compilers
Classifier: Topic :: Text Processing :: Linguistic
Classifier: Typing :: Typed
Requires-Python: >=3.10
License-File: LICENSE
Provides-Extra: core
Requires-Dist: tree-sitter~=0.24; extra == "core"
Dynamic: license-file
